{
  "$schema": "https://json.openmrs.org/routes.schema.json",
  "backendDependencies": {
    "fhir2": ">=1.2",
    "webservices.rest": "^2.24.0"
  },
  "extensions": [
    {
      "component": "imagingOrdersLink",
      "name": "radiology-dashboard-link",
      "slot":"homepage-dashboard-slot",
      "meta": {
        "name": "imaging-orders",
        "title": "imaging-orders",
        "slot": "imaging-dashboard-slot"
      }
    },
    {
      "component": "root",
      "name": "imaging-dashboard-root",
      "slot": "imaging-dashboard-slot"
    },
    {
     "component": "radiologyDashboard",
      "name": "radiology-dashboard-slot-name",
      "slot": "express-radiology-dashboard-slot"
    },
    {
      "name": "imaging-order-panel",
      "component": "imagingOrderPanel",
      "slot": "order-basket-slot",
      "order": 3
    }
  ],
  "workspaces": [
    {
      "name": "add-imaging-order",
      "type": "order",
      "component": "addImagingOrderWorkspace",
      "title": "Add Imaging order"
    },
    {
      "name": "imaging-report-form",
      "component": "imagingReportForm",
      "title": "Imaging Report Form",
      "type": "form"
    },
    {
      "name": "imaging-review-form",
      "type": "order",
      "component": "imagingReviewForm",
      "title": "Review form"
    },
    {
      "name": "search-patient-workspace",
      "component": "searchPatientWorkspace",
      "title": "Search patient",
      "type": "other-form"
    }
  ],
  "modals": [
    {
      "name": "reject-imaging-order-modal",
      "component": "rejectImagingOrderModal"
    },
    {
      "name": "add-imaging-to-work-list-modal",
      "component": "addImagingToWorkListModal"
    },
    {
      "name": "amend-imaging-order-modal",
      "component": "amendModal"
    },
    {
      "name": "print-preview-Report-modal",
      "component": "printReportModal"
    }
  ],
  "workspaceGroups": [
    {
      "name": "add-imaging-order-workspace-group",
      "members": [
        "add-drug-order",
        "order-basket",
        "add-lab-order",
        "add-imaging-order"
      ]
    }
  ]
}